{
  "interval": {
    "intervalStart": "2025-02-24T00:00:00.000Z",
    "intervalEnd": "2025-02-25T00:00:00.000Z",
    "intervalType": "day"
  },
  "repository": "elizaos-plugins/plugin-farcaster",
  "overview": "From 2025-02-24 to 2025-02-25, elizaos-plugins/plugin-farcaster had 0 new PRs (0 merged), 0 new issues, and 3 active contributors.",
  "topIssues": [],
  "topPRs": [],
  "codeChanges": {
    "additions": 0,
    "deletions": 0,
    "files": 0,
    "commitCount": 0
  },
  "completedItems": [],
  "topContributors": [
    {
      "username": "wtfsayo",
      "avatarUrl": "https://avatars.githubusercontent.com/u/82053242?u=98209a1f10456f42d4d2fa71db4d5bf4a672cbc3&v=4",
      "totalScore": 46.08939650691849,
      "prScore": 46.08939650691849,
      "issueScore": 0,
      "reviewScore": 0,
      "commentScore": 0,
      "summary": null
    },
    {
      "username": "tcm390",
      "avatarUrl": "https://avatars.githubusercontent.com/u/60634884?u=c6c41679b8322eaa0c81f72e0b4ed95e80f0ac16&v=4",
      "totalScore": 42.63501911726088,
      "prScore": 42.63501911726088,
      "issueScore": 0,
      "reviewScore": 0,
      "commentScore": 0,
      "summary": null
    },
    {
      "username": "odilitime",
      "avatarUrl": "https://avatars.githubusercontent.com/u/16395496?u=c9bac48e632aae594a0d85aaf9e9c9c69b674d8b&v=4",
      "totalScore": 42.142585092994054,
      "prScore": 22.302585092994047,
      "issueScore": 0,
      "reviewScore": 19.5,
      "commentScore": 0.33999999999999997,
      "summary": null
    },
    {
      "username": "fforbeck",
      "avatarUrl": "https://avatars.githubusercontent.com/u/708579?u=66ef82bcaf9ba0ea5840f7f9b89f5f5fb097a8b2&v=4",
      "totalScore": 33.5437738965761,
      "prScore": 33.5437738965761,
      "issueScore": 0,
      "reviewScore": 0,
      "commentScore": 0,
      "summary": null
    },
    {
      "username": "v1xingyue",
      "avatarUrl": "https://avatars.githubusercontent.com/u/974169?u=96c6a113a91978c041e5cf90965d7b66c5540af4&v=4",
      "totalScore": 30.13637738965761,
      "prScore": 25.63637738965761,
      "issueScore": 0,
      "reviewScore": 4.5,
      "commentScore": 0,
      "summary": null
    },
    {
      "username": "batudo",
      "avatarUrl": "https://avatars.githubusercontent.com/u/82539708?u=cd1f38be487e17b550d3bbd0e5f7b1a777d6baae&v=4",
      "totalScore": 28.299947636399185,
      "prScore": 23.799947636399185,
      "issueScore": 0,
      "reviewScore": 4.5,
      "commentScore": 0,
      "summary": null
    },
    {
      "username": "Doge-is-Dope",
      "avatarUrl": "https://avatars.githubusercontent.com/u/7845979?v=4",
      "totalScore": 27.878612288668112,
      "prScore": 27.878612288668112,
      "issueScore": 0,
      "reviewScore": 0,
      "commentScore": 0,
      "summary": null
    },
    {
      "username": "boolkeys",
      "avatarUrl": "https://avatars.githubusercontent.com/u/80537567?u=87099264c2c593567bd21af899a49aece2fc3274&v=4",
      "totalScore": 25.896866136776996,
      "prScore": 25.556866136776996,
      "issueScore": 0,
      "reviewScore": 0,
      "commentScore": 0.33999999999999997,
      "summary": null
    },
    {
      "username": "leopardracer",
      "avatarUrl": "https://avatars.githubusercontent.com/u/136604165?u=7ca681dd63a1e9991929157a38f094609d7a42f0&v=4",
      "totalScore": 23.4154379124341,
      "prScore": 23.4154379124341,
      "issueScore": 0,
      "reviewScore": 0,
      "commentScore": 0,
      "summary": null
    },
    {
      "username": "christopherpile",
      "avatarUrl": "https://avatars.githubusercontent.com/u/4848845?v=4",
      "totalScore": 11.437306144334055,
      "prScore": 11.437306144334055,
      "issueScore": 0,
      "reviewScore": 0,
      "commentScore": 0,
      "summary": null
    },
    {
      "username": "nusk0",
      "avatarUrl": "https://avatars.githubusercontent.com/u/36314459?u=aed9d177141f344a27f7bf9570b09024ecf6a6bb&v=4",
      "totalScore": 0.2,
      "prScore": 0,
      "issueScore": 0,
      "reviewScore": 0,
      "commentScore": 0.2,
      "summary": null
    }
  ],
  "newPRs": 0,
  "mergedPRs": 0,
  "newIssues": 0,
  "closedIssues": 0,
  "activeContributors": 3
}