{
  "version": "1.0",
  "type": "repository",
  "interval": "day",
  "generatedAt": "2025-12-19T23:12:51.007Z",
  "items": [
    {
      "date": "2025-12-19",
      "sourceLastUpdated": "2025-12-19T23:12:51.007Z",
      "contentHash": "50b45a1a4c4ffa81426aa4a575d06c198c7e0a3d6078d56ad93a25e8d907cbed",
      "path": "2025-12-19.json"
    },
    {
      "date": "2025-12-18",
      "sourceLastUpdated": "2025-12-19T23:12:47.294Z",
      "contentHash": "eb3a37a010432d6e55a78c016779813a9a879e42cdd9e784a0430eb8b7920713",
      "path": "2025-12-18.json"
    }
  ]
}