{
  "interval": {
    "intervalStart": "2026-01-17T00:00:00.000Z",
    "intervalEnd": "2026-01-18T00:00:00.000Z",
    "intervalType": "day"
  },
  "repository": "elizaos-plugins/plugin-coingecko",
  "overview": "From 2026-01-17 to 2026-01-18, elizaos-plugins/plugin-coingecko had 0 new PRs (0 merged), 0 new issues, and 1 active contributors.",
  "topIssues": [],
  "topPRs": [],
  "codeChanges": {
    "additions": 0,
    "deletions": 0,
    "files": 0,
    "commitCount": 0
  },
  "completedItems": [],
  "topContributors": [
    {
      "username": "YuriNachos",
      "avatarUrl": "https://avatars.githubusercontent.com/u/19365375?u=35202bfa8350f028db180527a789e8dcb7576d42&v=4",
      "totalScore": 249.18435236903713,
      "prScore": 248.98435236903714,
      "issueScore": 0,
      "reviewScore": 0,
      "commentScore": 0.2,
      "summary": "YuriNachos: Focused on a broad range of improvements, opening 10 PRs across bug fixes, new features, and documentation, including addressing authentication in agent commands (elizaos/eliza#6376, elizaos/eliza#6374) and adding an `unregisterAction` method to the core runtime (elizaos/eliza#6375, elizaos/eliza#6372), demonstrating a primary focus on bug fixes and feature development."
    },
    {
      "username": "greptile-apps",
      "avatarUrl": "https://avatars.githubusercontent.com/in/867647?v=4",
      "totalScore": 18.2,
      "prScore": 0,
      "issueScore": 0,
      "reviewScore": 18,
      "commentScore": 0.2,
      "summary": "greptile-apps: No activity today."
    },
    {
      "username": "borisudovicic",
      "avatarUrl": "https://avatars.githubusercontent.com/u/31806472?u=8935f4d43fd7e4eb9bf5ff92d54d4d2f8ac8a786&v=4",
      "totalScore": 2,
      "prScore": 0,
      "issueScore": 2,
      "reviewScore": 0,
      "commentScore": 0,
      "summary": "borisudovicic: Focused on product improvement by creating an issue in elizaos/eliza (#6381) to eliminate the 500-character limit in the first app prompt."
    },
    {
      "username": "Xayaan",
      "avatarUrl": "https://avatars.githubusercontent.com/u/5237930?u=7840b286463bde982c8af8f389e61e26a01328cb&v=4",
      "totalScore": 2,
      "prScore": 0,
      "issueScore": 2,
      "reviewScore": 0,
      "commentScore": 0,
      "summary": "Xayaan: Created one issue, elizaos/eliza#6380, to report a SQL error related to zero vector fallback."
    },
    {
      "username": "madjin",
      "avatarUrl": "https://avatars.githubusercontent.com/u/32600939?u=cdcf89f44c7a50906c7a80d889efa85023af2049&v=4",
      "totalScore": 0.43799999999999994,
      "prScore": 0,
      "issueScore": 0,
      "reviewScore": 0,
      "commentScore": 0.43799999999999994,
      "summary": "madjin: No activity today."
    }
  ],
  "newPRs": 0,
  "mergedPRs": 0,
  "newIssues": 0,
  "closedIssues": 0,
  "activeContributors": 1
}