{
  "interval": {
    "intervalStart": "2025-08-16T00:00:00.000Z",
    "intervalEnd": "2025-08-17T00:00:00.000Z",
    "intervalType": "day"
  },
  "repository": "elizaos-plugins/plugin-evm",
  "overview": "From 2025-08-16 to 2025-08-17, elizaos-plugins/plugin-evm had 0 new PRs (0 merged), 0 new issues, and 0 active contributors.",
  "topIssues": [],
  "topPRs": [],
  "codeChanges": {
    "additions": 0,
    "deletions": 0,
    "files": 0,
    "commitCount": 0
  },
  "completedItems": [],
  "topContributors": [
    {
      "username": "linear",
      "avatarUrl": "https://avatars.githubusercontent.com/in/20150?v=4",
      "totalScore": 24,
      "prScore": 0,
      "issueScore": 24,
      "reviewScore": 0,
      "commentScore": 0,
      "summary": null
    },
    {
      "username": "yungalgo",
      "avatarUrl": "https://avatars.githubusercontent.com/u/113615973?u=92e0f29f7e2fbb8ce46ed13c51f692ca803de02d&v=4",
      "totalScore": 0.2,
      "prScore": 0,
      "issueScore": 0,
      "reviewScore": 0,
      "commentScore": 0.2,
      "summary": null
    }
  ],
  "newPRs": 0,
  "mergedPRs": 0,
  "newIssues": 0,
  "closedIssues": 0,
  "activeContributors": 0
}