{
  "interval": {
    "intervalStart": "2025-07-29T00:00:00.000Z",
    "intervalEnd": "2025-07-30T00:00:00.000Z",
    "intervalType": "day"
  },
  "repository": "elizaos-plugins/plugin-evm",
  "overview": "From 2025-07-29 to 2025-07-30, elizaos-plugins/plugin-evm had 0 new PRs (0 merged), 0 new issues, and 1 active contributors.",
  "topIssues": [],
  "topPRs": [],
  "codeChanges": {
    "additions": 0,
    "deletions": 0,
    "files": 0,
    "commitCount": 0
  },
  "completedItems": [],
  "topContributors": [
    {
      "username": "HashWarlock",
      "avatarUrl": "https://avatars.githubusercontent.com/u/64296537?u=1d8228a93c06c603e08d438677b3f736d6b1ab22&v=4",
      "totalScore": 43.5437738965761,
      "prScore": 43.5437738965761,
      "issueScore": 0,
      "reviewScore": 0,
      "commentScore": 0,
      "summary": null
    },
    {
      "username": "0xbbjoker",
      "avatarUrl": "https://avatars.githubusercontent.com/u/54844437?u=90fe1762420de6ad493a1c1582f1f70c0d87d8e2&v=4",
      "totalScore": 25.622227826214598,
      "prScore": 25.622227826214598,
      "issueScore": 0,
      "reviewScore": 0,
      "commentScore": 0,
      "summary": null
    },
    {
      "username": "odilitime",
      "avatarUrl": "https://avatars.githubusercontent.com/u/16395496?u=c9bac48e632aae594a0d85aaf9e9c9c69b674d8b&v=4",
      "totalScore": 15.359866069401349,
      "prScore": 15.359866069401349,
      "issueScore": 0,
      "reviewScore": 0,
      "commentScore": 0,
      "summary": null
    },
    {
      "username": "ChristopherTrimboli",
      "avatarUrl": "https://avatars.githubusercontent.com/u/27584221?u=0d816ce1dcdea8f925aba18bb710153d4a87a719&v=4",
      "totalScore": 4.5,
      "prScore": 0,
      "issueScore": 0,
      "reviewScore": 4.5,
      "commentScore": 0,
      "summary": null
    },
    {
      "username": "samarth30",
      "avatarUrl": "https://avatars.githubusercontent.com/u/48334430?u=1fc119a6c2deb8cf60448b4c8961cb21dc69baeb&v=4",
      "totalScore": 2,
      "prScore": 0,
      "issueScore": 2,
      "reviewScore": 0,
      "commentScore": 0,
      "summary": null
    },
    {
      "username": "hesreallyhim",
      "avatarUrl": "https://avatars.githubusercontent.com/u/172150522?u=e288991976c46b53437a5880e90be140634a8477&v=4",
      "totalScore": 2,
      "prScore": 0,
      "issueScore": 2,
      "reviewScore": 0,
      "commentScore": 0,
      "summary": null
    }
  ],
  "newPRs": 0,
  "mergedPRs": 0,
  "newIssues": 0,
  "closedIssues": 0,
  "activeContributors": 1
}