{
  "interval": {
    "intervalStart": "2025-02-16T00:00:00.000Z",
    "intervalEnd": "2025-02-17T00:00:00.000Z",
    "intervalType": "day"
  },
  "repository": "elizaos-plugins/plugin-mcp",
  "overview": "From 2025-02-16 to 2025-02-17, elizaos-plugins/plugin-mcp had 0 new PRs (0 merged), 0 new issues, and 3 active contributors.",
  "topIssues": [],
  "topPRs": [],
  "codeChanges": {
    "additions": 0,
    "deletions": 0,
    "files": 0,
    "commitCount": 0
  },
  "completedItems": [],
  "topContributors": [
    {
      "username": "odilitime",
      "avatarUrl": "https://avatars.githubusercontent.com/u/16395496?u=c9bac48e632aae594a0d85aaf9e9c9c69b674d8b&v=4",
      "totalScore": 128.6815477931522,
      "prScore": 108.2435477931522,
      "issueScore": 0,
      "reviewScore": 20,
      "commentScore": 0.43799999999999994,
      "summary": null
    },
    {
      "username": "tcm390",
      "avatarUrl": "https://avatars.githubusercontent.com/u/60634884?u=c6c41679b8322eaa0c81f72e0b4ed95e80f0ac16&v=4",
      "totalScore": 102.38347442400845,
      "prScore": 92.38347442400845,
      "issueScore": 0,
      "reviewScore": 10,
      "commentScore": 0,
      "summary": null
    },
    {
      "username": "AIFlowML",
      "avatarUrl": "https://avatars.githubusercontent.com/u/154863472?u=99689ad0f9ec0be78ba3b726c1ef10df796fbe7d&v=4",
      "totalScore": 52.6657738965761,
      "prScore": 52.465773896576096,
      "issueScore": 0,
      "reviewScore": 0,
      "commentScore": 0.2,
      "summary": null
    },
    {
      "username": "mxchinegod",
      "avatarUrl": "https://avatars.githubusercontent.com/u/12659763?u=bc2c18c9e4ad867ecf12bead376b2f890e59264c&v=4",
      "totalScore": 45.776428824505615,
      "prScore": 45.776428824505615,
      "issueScore": 0,
      "reviewScore": 0,
      "commentScore": 0,
      "summary": null
    },
    {
      "username": "lggg123",
      "avatarUrl": "https://avatars.githubusercontent.com/u/22415259?u=210e0fb7c522442e99a3ccceabb2de94700509bb&v=4",
      "totalScore": 43.5437738965761,
      "prScore": 43.5437738965761,
      "issueScore": 0,
      "reviewScore": 0,
      "commentScore": 0,
      "summary": null
    },
    {
      "username": "yungalgo",
      "avatarUrl": "https://avatars.githubusercontent.com/u/113615973?u=92e0f29f7e2fbb8ce46ed13c51f692ca803de02d&v=4",
      "totalScore": 37.4677738965761,
      "prScore": 37.4677738965761,
      "issueScore": 0,
      "reviewScore": 0,
      "commentScore": 0,
      "summary": null
    },
    {
      "username": "andriyk-hacken",
      "avatarUrl": "https://avatars.githubusercontent.com/u/103185188?u=43258f70fa053157d4bfac6974430fa821e56123&v=4",
      "totalScore": 35.7697738965761,
      "prScore": 35.7697738965761,
      "issueScore": 0,
      "reviewScore": 0,
      "commentScore": 0,
      "summary": null
    },
    {
      "username": "mdqst",
      "avatarUrl": "https://avatars.githubusercontent.com/u/98899785?u=fd5aa4e17f3d730078504cd9afcbfc7d321224bc&v=4",
      "totalScore": 23.430013317336943,
      "prScore": 23.430013317336943,
      "issueScore": 0,
      "reviewScore": 0,
      "commentScore": 0,
      "summary": null
    },
    {
      "username": "w1ld3r",
      "avatarUrl": "https://avatars.githubusercontent.com/u/17899389?v=4",
      "totalScore": 15.138612288668108,
      "prScore": 14.798612288668108,
      "issueScore": 0,
      "reviewScore": 0,
      "commentScore": 0.33999999999999997,
      "summary": null
    },
    {
      "username": "ferraignez",
      "avatarUrl": "https://avatars.githubusercontent.com/u/199505620?v=4",
      "totalScore": 12.196530721670275,
      "prScore": 12.196530721670275,
      "issueScore": 0,
      "reviewScore": 0,
      "commentScore": 0,
      "summary": null
    },
    {
      "username": "eeemmmmmm",
      "avatarUrl": "https://avatars.githubusercontent.com/u/155267286?u=f7d609c472582d2c72ff5b592dddf98359459fc5&v=4",
      "totalScore": 4.80471895621705,
      "prScore": 4.80471895621705,
      "issueScore": 0,
      "reviewScore": 0,
      "commentScore": 0,
      "summary": null
    },
    {
      "username": "wolfskyknight",
      "avatarUrl": "https://avatars.githubusercontent.com/u/112670218?u=ea4748b1168804d1c7bab2d1d3d8238fc0c3cfad&v=4",
      "totalScore": 4.7379999999999995,
      "prScore": 0,
      "issueScore": 4.3,
      "reviewScore": 0,
      "commentScore": 0.43799999999999994,
      "summary": null
    },
    {
      "username": "github-advanced-security",
      "avatarUrl": "https://avatars.githubusercontent.com/in/57789?v=4",
      "totalScore": 4.5,
      "prScore": 0,
      "issueScore": 0,
      "reviewScore": 4.5,
      "commentScore": 0,
      "summary": null
    },
    {
      "username": "andyvalerio",
      "avatarUrl": "https://avatars.githubusercontent.com/u/11454941?u=246b3211ffd1c95ca1c845faa90c752a3d5f551b&v=4",
      "totalScore": 4.3,
      "prScore": 0,
      "issueScore": 4.1,
      "reviewScore": 0,
      "commentScore": 0.2,
      "summary": null
    }
  ],
  "newPRs": 0,
  "mergedPRs": 0,
  "newIssues": 0,
  "closedIssues": 0,
  "activeContributors": 3
}